qdrant_vector_aggregator/__init__.py
qdrant_vector_aggregator/aggregator.py
qdrant_vector_aggregator/config.py
qdrant_vector_aggregator/embedding_methods.py
qdrant_vector_aggregator/qdrant_collection_helpers.py
qdrant_vector_aggregator/utils.py
qdrant_vector_aggregator-1.0.2.dist-info/licenses/LICENSE
qdrant_vector_aggregator-1.0.2.dist-info/METADATA
qdrant_vector_aggregator-1.0.2.dist-info/WHEEL
qdrant_vector_aggregator-1.0.2.dist-info/top_level.txt
qdrant_vector_aggregator-1.0.2.dist-info/RECORD
