Metadata-Version: 2.4
Name: qdrant-vector-aggregator
Version: 1.0.2
Summary: Aggregate embeddings in Qdrant collections with smart content concatenation
Home-page: https://github.com/vinerya/qdrant_vector_aggregator
Author: Moudather Chelbi
Author-email: Moudather Chelbi <moudather.chelbi@gmail.com>
License: MIT
Project-URL: Homepage, https://github.com/vinerya/qdrant_vector_aggregator
Project-URL: Documentation, https://github.com/vinerya/qdrant_vector_aggregator#readme
Project-URL: Repository, https://github.com/vinerya/qdrant_vector_aggregator
Project-URL: Bug Tracker, https://github.com/vinerya/qdrant_vector_aggregator/issues
Keywords: qdrant,vector,embeddings,aggregation,semantic-search,nlp,machine-learning
Classifier: Development Status :: 4 - Beta
Classifier: Intended Audience :: Developers
Classifier: Intended Audience :: Science/Research
Classifier: License :: OSI Approved :: MIT License
Classifier: Operating System :: OS Independent
Classifier: Programming Language :: Python :: 3
Classifier: Programming Language :: Python :: 3.7
Classifier: Programming Language :: Python :: 3.8
Classifier: Programming Language :: Python :: 3.9
Classifier: Programming Language :: Python :: 3.10
Classifier: Programming Language :: Python :: 3.11
Classifier: Programming Language :: Python :: 3.12
Classifier: Topic :: Scientific/Engineering :: Artificial Intelligence
Classifier: Topic :: Software Development :: Libraries :: Python Modules
Classifier: Topic :: Database
Requires-Python: >=3.7
License-File: LICENSE
Requires-Dist: qdrant-client>=1.7.0
Requires-Dist: numpy>=1.21.0
Requires-Dist: scipy>=1.7.0
Requires-Dist: scikit-learn>=1.0.0
Requires-Dist: python-dotenv>=0.19.0
Provides-Extra: dev
Requires-Dist: pytest>=7.0.0; extra == "dev"
Requires-Dist: pytest-cov>=4.0.0; extra == "dev"
Requires-Dist: black>=22.0.0; extra == "dev"
Requires-Dist: flake8>=5.0.0; extra == "dev"
Requires-Dist: mypy>=0.990; extra == "dev"
Dynamic: author
Dynamic: home-page
Dynamic: license-file
Dynamic: requires-python
